{
    "usuarios": {
        "kassio": {
            "salt": "RqHYzhIO0AXWijtMlnoQGw==",
            "verificador": "81NR4YHE/1l1Yn4MdXNGaKECM032MyzfjVkOZKJaTuY="
        },
        "kassio12": {
            "salt": "LJ5x5MV1NzErJE1aIQlmWA==",
            "verificador": "wI9xY6rwb4ONJTr7wT6gR5FBr8NaJRVsoJjRuH/vOPE="
        },
        "AkinGOD777": {
            "salt": "+bvWM52ItwG5naWCo5rf1w==",
            "verificador": "elbQIPop94B39LhWVp6hQLmSpunWrxFEgZZQxcGSinw="
        },
        "SilvioSants": {
            "salt": "fpbF+WrETeuDX/bVFZGeUQ==",
            "verificador": "/9v8ycf5ihbTr7EnDHqQ747g5PEgrHKnfE8unfAzDMU="
        }
    }
}